gencardhks/__init__.py
gencardhks/hks.py
gencardhks-1.0.5.dist-info/LICENSE
gencardhks-1.0.5.dist-info/METADATA
gencardhks-1.0.5.dist-info/WHEEL
gencardhks-1.0.5.dist-info/top_level.txt
gencardhks-1.0.5.dist-info/RECORD
